dataviz/__init__.py
dataviz/backend_bokeh.py
dataviz/backend_datashader.py
dataviz/backend_matplotlib.py
dataviz/utils.py
dataviz-1.1.0.dist-info/LICENSE.txt
dataviz-1.1.0.dist-info/METADATA
dataviz-1.1.0.dist-info/WHEEL
dataviz-1.1.0.dist-info/top_level.txt
dataviz-1.1.0.dist-info/RECORD
