Metadata-Version: 2.1
Name: dataviz
Version: 1.1.0
Summary: Create plots quickly
Home-page: https://gitlab.com/librecube/lib/python-dataviz
Author-email: info@librecube.org
License: MIT
Platform: UNKNOWN
Requires-Python: >=3
License-File: LICENSE.txt
Requires-Dist: requests
Requires-Dist: numpy
Requires-Dist: pandas
Requires-Dist: matplotlib
Requires-Dist: bokeh
